{
  "_meta": {
    "version": "2026-04-17",
    "source": "SCHEDULE -EPC BOROUGE.xlsx (col J = MS flag)",
    "project": "Borouge EU3 H2 Extraction EPC",
    "note": "Update forecast_finish and done fields after each schedule upload"
  },
  "milestones": [
    {
      "id": "LOA",
      "label": "Letter of Award (LOA)",
      "activity_id": "A1-PM-PMM-0001",
      "category": "Contract",
      "forecast_finish": "2024-11-07",
      "early_finish": "2024-11-07",
      "done": true,
      "key": true,
      "variance_days": 0,
      "description": "Contract award — project start signal. Marks the official commencement of the EPC contract.",
      "responsible": "Owner / COMPANY",
      "notes": ""
    },
    {
      "id": "KOM",
      "label": "10.A-Kick-off Meeting Completed",
      "activity_id": "A1-PM-PMM-0002",
      "category": "Project Management",
      "forecast_finish": "2024-12-06",
      "early_finish": "2024-12-06",
      "done": true,
      "key": false,
      "variance_days": 116,
      "description": "Formal kick-off meeting with all key stakeholders. Baseline schedule and interfaces agreed.",
      "responsible": "PMT",
      "notes": "Finish variance 116 days in Feb-2026 data"
    },
    {
      "id": "PPF",
      "label": "113.E-Start Piping Prefabrication",
      "activity_id": "A1-PM-CIM-0024",
      "category": "Engineering",
      "forecast_finish": "2025-03-25",
      "early_finish": "2025-03-25",
      "done": true,
      "key": false,
      "variance_days": -4,
      "description": "Start of piping prefabrication works at workshop. Approval of vendor data for FG & OG compressor required.",
      "responsible": "Engineering / Subcontract",
      "notes": "Finish variance -4 days (slightly ahead)"
    },
    {
      "id": "PPS",
      "label": "117.E-Start Piping Erection",
      "activity_id": "A1-PM-CIM-0028",
      "category": "Construction",
      "forecast_finish": "2025-04-15",
      "early_finish": "2025-04-15",
      "done": true,
      "key": false,
      "variance_days": 0,
      "description": "Start of piping erection works on site.",
      "responsible": "Construction / Subcontract",
      "notes": ""
    },
    {
      "id": "EPR",
      "label": "1.A*-Issue Engineering Procedure",
      "activity_id": "A1-PM-EIM-0001",
      "category": "Engineering",
      "forecast_finish": "2025-04-30",
      "early_finish": "2025-04-30",
      "done": true,
      "key": false,
      "variance_days": 0,
      "description": "Issue of engineering procedures and standards documentation to site.",
      "responsible": "Engineering",
      "notes": ""
    },
    {
      "id": "TA",
      "label": "Turnaround Scope Completion (TA)",
      "activity_id": "A1-PM-PKM-0001",
      "category": "Construction",
      "forecast_finish": "2025-05-17",
      "early_finish": "2025-05-17",
      "done": true,
      "key": true,
      "variance_days": 0,
      "description": "Completion of all turnaround scope items. Gate milestone before main construction ramp.",
      "responsible": "Construction",
      "notes": ""
    },
    {
      "id": "COM",
      "label": "94.E*-Commence on SITE",
      "activity_id": "A1-PM-CIM-0011",
      "category": "Construction",
      "forecast_finish": "2025-05-31",
      "early_finish": "2025-05-31",
      "done": true,
      "key": false,
      "variance_days": 0,
      "description": "Official commencement of construction activities on site.",
      "responsible": "Construction",
      "notes": ""
    },
    {
      "id": "E60",
      "label": "Engineering Workshops — 60% Model Review",
      "activity_id": "A1-PM-EWS-0002",
      "category": "Engineering",
      "forecast_finish": "2025-09-19",
      "early_finish": "2025-09-19",
      "done": true,
      "key": false,
      "variance_days": 0,
      "description": "60% 3D model review workshop with owner and engineering team. Freeze on major design decisions.",
      "responsible": "Engineering",
      "notes": ""
    },
    {
      "id": "OGC",
      "label": "Off Gas Compressor delivery",
      "activity_id": "A62380",
      "category": "Procurement",
      "forecast_finish": "2026-03-01",
      "early_finish": "2026-02-06",
      "done": true,
      "key": false,
      "variance_days": 23,
      "description": "OG Compressor delivered to site. Delivery was delayed vs early finish date.",
      "responsible": "Vendor / Procurement",
      "notes": "Early finish was 6 Feb, actual delivery ~1 Mar"
    },
    {
      "id": "E90",
      "label": "Engineering Workshops — 90% Model Review",
      "activity_id": "A1-PM-EWS-0003",
      "category": "Engineering",
      "forecast_finish": "2026-03-06",
      "early_finish": "2026-03-15",
      "done": true,
      "key": true,
      "variance_days": 0,
      "description": "90% 3D model review workshop. Final IFC package sign-off. Construction drawings released.",
      "responsible": "Engineering",
      "notes": "Forecast 15 Mar, early 6 Mar"
    },
    {
      "id": "101",
      "label": "101.E-Complete all Piperack foundations",
      "activity_id": "A1-PM-CIM-0015",
      "category": "Construction",
      "forecast_finish": "2026-04-09",
      "early_finish": "2026-05-25",
      "done": false,
      "key": false,
      "variance_days": 46,
      "description": "Completion of all piperack foundation concrete works. Prerequisite for structural steel erection.",
      "responsible": "Construction Civil",
      "notes": ""
    },
    {
      "id": "FGC",
      "label": "76.D*-Compressors delivered to SITE",
      "activity_id": "A62300",
      "category": "Procurement",
      "forecast_finish": "2026-06-22",
      "early_finish": "2026-03-03",
      "done": false,
      "key": true,
      "variance_days": 111,
      "description": "FG Compressor (and associated equipment) delivered to site. CRITICAL — 111 days late, drives all downstream construction.",
      "responsible": "Vendor / Procurement",
      "notes": "Worst slip on CP: +111d. Early finish was 3 Mar 2026."
    },
    {
      "id": "FGA",
      "label": "Feed Gas Compressor (Baseplate, Gear, Gas Seal)",
      "activity_id": "A62300",
      "category": "Procurement",
      "forecast_finish": "2026-06-22",
      "early_finish": "2026-03-03",
      "done": false,
      "key": false,
      "variance_days": 111,
      "description": "FG Compressor baseplate, gearbox and gas seal components delivered. Part of the FGC delivery package.",
      "responsible": "Vendor",
      "notes": ""
    },
    {
      "id": "110",
      "label": "110.E-Complete installation Turbines/Compressors",
      "activity_id": "A1-PM-CIM-0021",
      "category": "Construction",
      "forecast_finish": "2026-07-19",
      "early_finish": "2026-05-18",
      "done": false,
      "key": false,
      "variance_days": 62,
      "description": "Complete mechanical installation of all turbines and compressors on their foundations.",
      "responsible": "Construction Mechanical",
      "notes": ""
    },
    {
      "id": "102",
      "label": "102.E-Complete all underground piping",
      "activity_id": "A1-PM-CIM-0016",
      "category": "Construction",
      "forecast_finish": "2026-08-19",
      "early_finish": "2026-07-19",
      "done": false,
      "key": false,
      "variance_days": 31,
      "description": "Completion of all underground piping, including buried utilities and process lines.",
      "responsible": "Construction Piping",
      "notes": ""
    },
    {
      "id": "86D",
      "label": "86.D*-Bulk piping materials final MTO to SITE",
      "activity_id": "A1-PM-PRM-0035",
      "category": "Procurement",
      "forecast_finish": "2026-09-17",
      "early_finish": "2026-08-22",
      "done": false,
      "key": false,
      "variance_days": 26,
      "description": "Final bulk piping materials (valves, fittings, pipe) delivered to site per final MTO.",
      "responsible": "Procurement",
      "notes": ""
    },
    {
      "id": "88D",
      "label": "88.D-Bulk electrical materials final MTO to SITE",
      "activity_id": "A1-PM-PRM-0036",
      "category": "Procurement",
      "forecast_finish": "2026-09-28",
      "early_finish": "2026-08-31",
      "done": false,
      "key": false,
      "variance_days": 28,
      "description": "Final bulk electrical materials (cable, conduit, accessories) delivered to site.",
      "responsible": "Procurement",
      "notes": ""
    },
    {
      "id": "90D",
      "label": "90.D-Bulk instrument materials final MTO to SITE",
      "activity_id": "A1-PM-PRM-0037",
      "category": "Procurement",
      "forecast_finish": "2026-10-19",
      "early_finish": "2026-09-24",
      "done": false,
      "key": false,
      "variance_days": 25,
      "description": "Final bulk instrument materials delivered to site.",
      "responsible": "Procurement",
      "notes": ""
    },
    {
      "id": "82D",
      "label": "82.D-Instrument Control SYSTEMS for CCB to SITE",
      "activity_id": "A1-PM-PRM-0031",
      "category": "Procurement",
      "forecast_finish": "2026-10-30",
      "early_finish": "2026-09-29",
      "done": false,
      "key": false,
      "variance_days": 31,
      "description": "Instrument control systems (DCS/SIS panels, CCB equipment) delivered to site.",
      "responsible": "Procurement",
      "notes": ""
    },
    {
      "id": "79D",
      "label": "79.D*-All major electrical Equipment to SITE",
      "activity_id": "A1-PM-PRM-0028",
      "category": "Procurement",
      "forecast_finish": "2026-10-30",
      "early_finish": "2026-09-29",
      "done": false,
      "key": false,
      "variance_days": 31,
      "description": "All major electrical equipment (MV/LV switchgear, transformers, MCC) delivered to site.",
      "responsible": "Procurement",
      "notes": ""
    },
    {
      "id": "115",
      "label": "115.E-Complete prefabrication 98% piping",
      "activity_id": "A1-PM-CIM-0026",
      "category": "Construction",
      "forecast_finish": "2026-10-26",
      "early_finish": "2026-10-05",
      "done": false,
      "key": false,
      "variance_days": 21,
      "description": "98% completion of all piping prefabrication (spools, assemblies) at workshop and laydown.",
      "responsible": "Construction Piping",
      "notes": ""
    },
    {
      "id": "81D",
      "label": "81.D*-Major instrument control SYSTEMS to SITE",
      "activity_id": "A1-PM-PRM-0030",
      "category": "Procurement",
      "forecast_finish": "2026-11-06",
      "early_finish": "2026-09-29",
      "done": false,
      "key": false,
      "variance_days": 38,
      "description": "Major instrument and control system packages delivered to site (analyser shelter, fire & gas system).",
      "responsible": "Procurement",
      "notes": ""
    },
    {
      "id": "83D",
      "label": "83.D-Field instrument tagged items to SITE",
      "activity_id": "A1-PM-PRM-0032",
      "category": "Procurement",
      "forecast_finish": "2026-11-06",
      "early_finish": "2026-09-27",
      "done": false,
      "key": false,
      "variance_days": 40,
      "description": "All field-tagged instrument items (transmitters, control valves, gauges) delivered to site.",
      "responsible": "Procurement",
      "notes": ""
    },
    {
      "id": "125",
      "label": "125.E-Complete Heat Tracing, Insulation & Painting",
      "activity_id": "A1-PM-CIM-0036",
      "category": "Construction",
      "forecast_finish": "2026-11-07",
      "early_finish": "2026-10-05",
      "done": false,
      "key": false,
      "variance_days": 33,
      "description": "Completion of all heat tracing installations, pipe insulation and surface painting.",
      "responsible": "Construction",
      "notes": ""
    },
    {
      "id": "STL",
      "label": "106.E-Complete steel structural works",
      "activity_id": "A1-PM-CIM-0020",
      "category": "Construction",
      "forecast_finish": "2026-11-11",
      "early_finish": "2026-09-10",
      "done": false,
      "key": true,
      "variance_days": 62,
      "description": "Completion of all structural steel erection and bolting. Includes pipe racks SR81 and compressor area.",
      "responsible": "Construction Steel",
      "notes": ""
    },
    {
      "id": "119",
      "label": "119.E-Piping Erection 100% complete",
      "activity_id": "A1-PM-CIM-0030",
      "category": "Construction",
      "forecast_finish": "2026-11-14",
      "early_finish": "2026-10-22",
      "done": false,
      "key": false,
      "variance_days": 23,
      "description": "100% completion of all above-ground piping erection works.",
      "responsible": "Construction Piping",
      "notes": ""
    },
    {
      "id": "122",
      "label": "122.E-Piping Hydrotesting 100% complete",
      "activity_id": "A1-PM-CIM-0033",
      "category": "Construction",
      "forecast_finish": "2026-12-07",
      "early_finish": "2026-12-03",
      "done": false,
      "key": false,
      "variance_days": 4,
      "description": "100% completion of all piping hydrotest, leak test, and reinstatement activities.",
      "responsible": "Construction / Pre-commissioning",
      "notes": ""
    },
    {
      "id": "129",
      "label": "129.E-Complete electrical cabling & termination",
      "activity_id": "A1-PM-CIM-0040",
      "category": "Construction",
      "forecast_finish": "2026-12-28",
      "early_finish": "2026-12-21",
      "done": false,
      "key": false,
      "variance_days": 7,
      "description": "Completion of all electrical cable pulling, glanding and termination works.",
      "responsible": "Construction Electrical",
      "notes": ""
    },
    {
      "id": "136",
      "label": "136.E-Complete instrumentation loop checks",
      "activity_id": "A1-PM-CIM-0045",
      "category": "Construction",
      "forecast_finish": "2026-12-28",
      "early_finish": "2026-12-21",
      "done": false,
      "key": false,
      "variance_days": 7,
      "description": "Completion of all instrument loop checks, calibration and functional testing.",
      "responsible": "Construction Instrumentation",
      "notes": ""
    },
    {
      "id": "ANZ",
      "label": "Analyzer (PO pending) — delivery",
      "activity_id": "A62480",
      "category": "Procurement",
      "forecast_finish": "2026-12-31",
      "early_finish": "2026-10-07",
      "done": false,
      "key": false,
      "variance_days": 85,
      "description": "Process analyser package delivery to site. PO was pending at time of baseline — high risk item.",
      "responsible": "Procurement",
      "notes": "PO still pending at baseline — high procurement risk"
    },
    {
      "id": "ABT",
      "label": "8.A*-As Built drawings handover to COMPANY",
      "activity_id": "A1-PM-EIM-0002",
      "category": "Engineering",
      "forecast_finish": "2027-01-21",
      "early_finish": "2027-03-24",
      "done": false,
      "key": false,
      "variance_days": 0,
      "description": "Handover of all as-built drawings, marked-up P&IDs and engineering documents to COMPANY.",
      "responsible": "Engineering",
      "notes": ""
    },
    {
      "id": "MC",
      "label": "138.F-Mechanical Completion",
      "activity_id": "A1-PM-PKM-0002",
      "category": "Milestone",
      "forecast_finish": "2027-03-23",
      "early_finish": "2027-01-20",
      "done": false,
      "key": true,
      "variance_days": 62,
      "description": "Mechanical Completion — all physical installation work completed, punch list category A cleared. Baseline was 20 Jan 2027, slipped +62d to 23 Mar 2027 due to FG Compressor delivery delay.",
      "responsible": "Construction / PMT",
      "notes": "Baseline: 20 Jan 2027 → Forecast: 23 Mar 2027 (+62d)"
    },
    {
      "id": "RFSU",
      "label": "Ready for Start-up (RFSU)",
      "activity_id": "A1-PM-PKM-0003",
      "category": "Milestone",
      "forecast_finish": "2027-06-22",
      "early_finish": "2027-04-21",
      "done": false,
      "key": true,
      "variance_days": 62,
      "description": "Ready for Start-up — all pre-commissioning activities complete, utilities available, systems ready for introduction of process fluids.",
      "responsible": "Commissioning / PMT",
      "notes": "Baseline: 21 Apr 2027 → Forecast: 22 Jun 2027 (+62d)"
    },
    {
      "id": "PAC",
      "label": "Provisional Acceptance Certificate (PAC)",
      "activity_id": "A1-PM-PKM-0004",
      "category": "Milestone",
      "forecast_finish": "2027-09-20",
      "early_finish": "2027-07-20",
      "done": false,
      "key": true,
      "variance_days": 62,
      "description": "Provisional Acceptance Certificate issued by COMPANY after successful commissioning and performance testing.",
      "responsible": "PMT / COMPANY",
      "notes": "Baseline: 20 Jul 2027 → Forecast: 20 Sep 2027 (+62d)"
    }
  ]
}
